{
  "type": "Feature",
  "properties": {
    "gn:admin1_code":"0.0",
    "gn:asciiname":"Lower Valley",
    "gn:country_code":"KY",
    "gn:dem":6,
    "gn:feature_class":"P",
    "gn:feature_code":"PPL",
    "gn:name":"Lower Valley",
    "gn:population":0,
    "gn:timezone":"America/Cayman",
    "iso:country":"KY",
    "wof:name":"Lower Valley",
    "wof:placetype":"locality"
},
  "geometry": {"coordinates":[-81.28333000000001,19.28333],"type":"Point"}
}