{
  "type": "Feature",
  "properties": {
    "gn:admin1_code":"0.0",
    "gn:asciiname":"Upper Land",
    "gn:country_code":"KY",
    "gn:dem":9,
    "gn:feature_class":"P",
    "gn:feature_code":"PPL",
    "gn:name":"Upper Land",
    "gn:population":0,
    "gn:timezone":"America/Cayman",
    "iso:country":"KY",
    "wof:name":"Upper Land",
    "wof:placetype":"locality"
},
  "geometry": {"coordinates":[-81.38333,19.35],"type":"Point"}
}