{
  "type": "Feature",
  "properties": {
    "gn:admin1_code":"0.0",
    "gn:asciiname":"Red Bay Estate",
    "gn:cc2":"KY",
    "gn:country_code":"KY",
    "gn:dem":6,
    "gn:feature_class":"P",
    "gn:feature_code":"PPL",
    "gn:name":"Red Bay Estate",
    "gn:population":0,
    "gn:timezone":"America/Cayman",
    "iso:country":"KY",
    "name:und_x_variant":[
        "Red Bay",
        "Red Bay Estate"
    ],
    "wof:name":"Red Bay Estate",
    "wof:placetype":"locality"
},
  "geometry": {"coordinates":[-81.34999999999999,19.28333],"type":"Point"}
}