{
  "type": "Feature",
  "properties": {
    "gn:asciiname":"Rum Point",
    "gn:country_code":"KY",
    "gn:dem":7,
    "gn:feature_class":"P",
    "gn:feature_code":"PPL",
    "gn:name":"Rum Point",
    "gn:population":0,
    "gn:timezone":"America/Cayman",
    "iso:country":"KY",
    "wof:name":"Rum Point",
    "wof:placetype":"locality"
},
  "geometry": {"coordinates":[-81.26145,19.36415],"type":"Point"}
}