{
  "type": "Feature",
  "properties": {
    "gn:admin1_code":"0.0",
    "gn:asciiname":"Pease Bay",
    "gn:country_code":"KY",
    "gn:dem":5,
    "gn:feature_class":"P",
    "gn:feature_code":"PPL",
    "gn:name":"Pease Bay",
    "gn:population":0,
    "gn:timezone":"America/Cayman",
    "iso:country":"KY",
    "wof:name":"Pease Bay",
    "wof:placetype":"locality"
},
  "geometry": {"coordinates":[-81.24166,19.28781],"type":"Point"}
}